django_eremaea2-2.1.1.dist-info/licenses/LICENSE
eremaea/__init__.py
eremaea/conf.py
eremaea/models.py
eremaea/serializers.py
eremaea/urls.py
eremaea/views.py
eremaea/ctl/__init__.py
eremaea/ctl/client.py
eremaea/ctl/commandline.py
eremaea/ctl/file.py
eremaea/migrations/0001_squashed_0002_drop_index_together.py
eremaea/migrations/0003_initial_retention_policies.py
eremaea/migrations/0004_use_slug_for_names.py
eremaea/migrations/__init__.py
django_eremaea2-2.1.1.dist-info/METADATA
django_eremaea2-2.1.1.dist-info/WHEEL
django_eremaea2-2.1.1.dist-info/entry_points.txt
django_eremaea2-2.1.1.dist-info/top_level.txt
django_eremaea2-2.1.1.dist-info/RECORD
