Metadata-Version: 2.4
Name: django-eremaea2
Version: 2.1.1
Summary: A simple Django application to store and show webcam snapshots
Author-email: "Matwey V. Kornilov" <matwey.kornilov@gmail.com>
License: BSD-2-Clause
Project-URL: Repository, https://github.com/matwey/django-eremaea2.git
Project-URL: Issues, https://github.com/matwey/django-eremaea2/issues
Classifier: Development Status :: 5 - Production/Stable
Classifier: Environment :: Web Environment
Classifier: Framework :: Django
Classifier: Intended Audience :: Developers
Classifier: License :: OSI Approved :: BSD License
Classifier: Operating System :: OS Independent
Classifier: Programming Language :: Python :: 3
Classifier: Programming Language :: Python
Classifier: Topic :: Internet :: WWW/HTTP :: Dynamic Content
Classifier: Topic :: Internet :: WWW/HTTP
Requires-Python: >=3.7
License-File: LICENSE
Requires-Dist: click
Requires-Dist: django-filter
Requires-Dist: djangorestframework
Requires-Dist: drf_spectacular
Requires-Dist: python-magic
Requires-Dist: requests
Requires-Dist: requests_toolbelt
Provides-Extra: dev
Requires-Dist: Django>=4.2; extra == "dev"
Requires-Dist: mock; extra == "dev"
Requires-Dist: pytest; extra == "dev"
Requires-Dist: pytest-django; extra == "dev"
Requires-Dist: requests-mock; extra == "dev"
Dynamic: license-file
